boostflask/__about__.py
boostflask/__init__.py
boostflask/_config.py
boostflask/_typing.py
boostflask/_utils.py
boostflask/bootstrap.py
boostflask/context.py
boostflask/error_handler.py
boostflask/pool.py
boostflask/py.typed
boostflask/task.py
boostflask/view/__init__.py
boostflask/view/base.py
boostflask/view/decorator.py
boostflask/view/renderer.py
boostflask/view/resolver/__init__.py
boostflask/view/resolver/_utils.py
boostflask/view/resolver/base.py
boostflask/view/resolver/standard.py
boostflask/view/resolver/types.py
boost_flask-0.0.1.dev12.dist-info/METADATA
boost_flask-0.0.1.dev12.dist-info/WHEEL
boost_flask-0.0.1.dev12.dist-info/licenses/LICENSE
boost_flask-0.0.1.dev12.dist-info/RECORD
