Metadata-Version: 2.4
Name: boost-flask
Version: 0.0.1.dev12
Summary: Develop Flask app in a simple way.
Project-URL: Homepage, https://github.com/deadblue/boost-flask
Project-URL: Repository, https://github.com/deadblue/boost-flask
Author-email: deadblue <root@dead.blue>
License: MIT License
License-File: LICENSE
Classifier: Development Status :: 3 - Alpha
Classifier: Environment :: Web Environment
Classifier: Framework :: Flask
Classifier: License :: OSI Approved :: MIT License
Classifier: Operating System :: OS Independent
Classifier: Programming Language :: Python
Classifier: Programming Language :: Python :: 3
Classifier: Programming Language :: Python :: 3.11
Classifier: Programming Language :: Python :: 3.12
Classifier: Topic :: Internet :: WWW/HTTP :: HTTP Servers
Classifier: Topic :: Internet :: WWW/HTTP :: WSGI :: Application
Requires-Python: >=3.11
Requires-Dist: flask<4,>=3.0.0
